midani/__init__.py
midani/__main__.py
midani/midani_annotations.py
midani/midani_av.py
midani/midani_colors.py
midani/midani_misc_classes.py
midani/midani_plot.py
midani/midani_r.py
midani/midani_score.py
midani/midani_settings.py
midani/midani_time.py
midani/multi_boss.py
midani/plt_boss.py
midani/from_my_other_projects/__init__.py
midani/from_my_other_projects/mal_misc.py
midani/from_my_other_projects/midi_funcs.py
midani/from_my_other_projects/note_classes.py
midani/from_my_other_projects/tuning.py
midani-0.0.3.dist-info/LICENSE
midani-0.0.3.dist-info/METADATA
midani-0.0.3.dist-info/WHEEL
midani-0.0.3.dist-info/entry_points.txt
midani-0.0.3.dist-info/top_level.txt
midani-0.0.3.dist-info/RECORD
