Metadata-Version: 2.1
Name: midani
Version: 0.0.3
Summary: Make piano-roll animations from midi files
Home-page: https://github.com/malcolmsailor/midani
Author: Malcolm Sailor
Author-email: malcolm.sailor@gmail.com
License: UNKNOWN
Project-URL: Bug Tracker, https://github.com/malcolmsailor/midani/issues
Platform: UNKNOWN
Classifier: Programming Language :: Python :: 3
Classifier: License :: OSI Approved :: MIT License
Classifier: Operating System :: OS Independent
Requires-Python: >=3.8
License-File: LICENSE
Requires-Dist: opencv-python
Requires-Dist: mido
